chargesats/__init__.py
chargesats/charger.py
chargesats-0.1.1.dist-info/METADATA
chargesats-0.1.1.dist-info/WHEEL
chargesats-0.1.1.dist-info/RECORD
