Metadata-Version: 2.1
Name: chargesats
Version: 0.1.1
Summary: A decorator library for Flask endpoints, to create CLN invoices
Author: niftynei
Author-email: niftynei@gmail.com
Requires-Python: >=3.10,<4.0
Classifier: Programming Language :: Python :: 3
Classifier: Programming Language :: Python :: 3.10
Classifier: Programming Language :: Python :: 3.11
Requires-Dist: flask (>=2.3.2,<3.0.0)
Requires-Dist: pyln-client (>=23.5.2,<24.0.0)
